torob/__init__.py
torob/att.py
torob/city.py
torob/torob.py
torob/torobot_documentation.pdf
torob/image/main-bg.png
torob/image/main-nm.png
torob/image/main.png
torob/image/orginal.png
torob-1.1.dist-info/METADATA
torob-1.1.dist-info/WHEEL
torob-1.1.dist-info/licenses/LICENSE
torob-1.1.dist-info/RECORD
