Metadata-Version: 2.3
Name: torob
Version: 1.1
Summary: Search for goods and stores on torob.com 🍎
Project-URL: Homepage, https://github.com/itsMajid-dev/torobot
Project-URL: Issues, https://github.com/pypa/sampleproject/issues
Author-email: itsMajid <itsMajid.dev@gmail.com>
License-File: LICENSE
Classifier: License :: OSI Approved :: MIT License
Classifier: Operating System :: OS Independent
Classifier: Programming Language :: Python :: 3
Requires-Python: >=3.8
Requires-Dist: beautifulsoup4>4.9.3
Requires-Dist: pandas>1.2.4
Requires-Dist: requests>2.25.1
